djapps
