Metadata-Version: 1.0
Name: djapps
Version: 0.1.1
Summary: Load your django apps by app name rather than module path.
Home-page: https://github.com/RichardOfWard/djapps
Author: Richard Ward
Author-email: richard@richard.ward.name
License: BSD
Platform: UNKNOWN
